[
  {
    "name": "Cola"
  },
  {
    "name": "Ginger"
  },
  {
    "name": "Rum"
  },
  {
    "name": "Vodka"
  },
  {
    "name": "Bourbon whiskey"
  },
  {
    "name": "Scotch whiskey"
  },
  {
    "name": "Angostura"
  },
  {
    "name": "Triple sec liqueur"
  },
  {
    "name": "Tequila"
  },
  {
    "name": "Mezcal"
  },
  {
    "name": "Amaro"
  },
  {
    "name": "Cachaça"
  },
  {
    "name": "Lime"
  },
  {
    "name": "Lemon"
  },
  {
    "name": "Pinapple"
  },
  {
    "name": "Jägermeister"
  },
  {
    "name": "Akvavit"
  },
  {
    "name": "Wine"
  },
  {
    "name": "Beer"
  }
]
